README.md
setup.py
bplist/__init__.py
bplist/bplist.py
bplist.egg-info/PKG-INFO
bplist.egg-info/SOURCES.txt
bplist.egg-info/dependency_links.txt
bplist.egg-info/top_level.txt