Metadata-Version: 1.0
Name: bplist
Version: 1.0
Summary: Apple binary Property List reader/writer for Python
Home-page: https://github.com/farcaller/bplist-python
Author: Vladimir Pouzanov
Author-email: farcaller@gmail.com
License: MIT
Keywords: bplist
Platform: UNKNOWN
